gumo/__init__.py
gumo/storage/__init__.py
gumo/storage/infrastructure/__init__.py
gumo_storage-0.1.1.dist-info/LICENSE
gumo_storage-0.1.1.dist-info/METADATA
gumo_storage-0.1.1.dist-info/WHEEL
gumo_storage-0.1.1.dist-info/top_level.txt
gumo_storage-0.1.1.dist-info/RECORD
