Metadata-Version: 2.1
Name: gumo-storage
Version: 0.1.1
Summary: Gumo Storage Library
Home-page: https://github.com/gumo-py/gumo-storage
Author: Gumo Project Team
Author-email: gumo-py@googlegroups.com
License: UNKNOWN
Platform: UNKNOWN
Classifier: Programming Language :: Python :: 3
Classifier: License :: OSI Approved :: MIT License
Classifier: Operating System :: OS Independent
Requires-Dist: gumo-core (>=0.1.0)
